shortcutml/feature_selection/UnivariateFeatureSelection.py
shortcutml/feature_selection/__init__.py
shortcutml/model_selection/AutoSearchCV.py
shortcutml/model_selection/BaselineModel.py
shortcutml/model_selection/__init__.py
shortcutml/preprocessing/TextCleaningIndo.py
shortcutml/preprocessing/__init__.py
shortcutml-0.8.dist-info/LICENSE
shortcutml-0.8.dist-info/METADATA
shortcutml-0.8.dist-info/WHEEL
shortcutml-0.8.dist-info/top_level.txt
shortcutml-0.8.dist-info/RECORD
