Metadata-Version: 2.1
Name: shortcutml
Version: 0.8
Summary: Machine learning baseline prototyping tools
Home-page: https://github.com/SulthanAbiyyu/ShortcutML
Author: Sulthan Abiyyu Hakim
Author-email: sabiyyuhakim@student.ub.ac.id
License: MIT
Download-URL: https://github.com/SulthanAbiyyu/ShortcutML/archive/refs/tags/0.8.tar.gz
Keywords: machine learning,summary
Platform: UNKNOWN
Classifier: Development Status :: 3 - Alpha
Classifier: Intended Audience :: Developers
Classifier: Topic :: Software Development :: Build Tools
Classifier: License :: OSI Approved :: MIT License
Classifier: Programming Language :: Python :: 3.8
Classifier: Programming Language :: Python :: 3.9
License-File: LICENSE
Requires-Dist: joblib
Requires-Dist: lightgbm
Requires-Dist: matplotlib
Requires-Dist: numpy
Requires-Dist: pandas
Requires-Dist: PySastrawi
Requires-Dist: scikit-learn
Requires-Dist: seaborn
Requires-Dist: xgboost
